{"tortoises": [{"id": 0, "top": 963994, "position": 95435406}, {"id": 1, "top": 963994, "position": 184663357}, {"id": 2, "top": 963994, "position": 53059906}, {"id": 3, "top": 963994, "position": 214631452}, {"id": 4, "top": 963994, "position": 181834961}, {"id": 5, "top": 963994, "position": 188887594}, {"id": 6, "top": 963994, "position": 257466332}, {"id": 7, "top": 963994, "position": 169312867}, {"id": 8, "top": 963994, "position": 223627976}, {"id": 9, "top": 963994, "position": 115564530}, {"id": 10, "top": 963994, "position": 128050808}, {"id": 11, "top": 963994, "position": 165807896}, {"id": 12, "top": 963994, "position": 256710773}, {"id": 13, "top": 963994, "position": 332145410}, {"id": 14, "top": 963994, "position": 171590932}, {"id": 15, "top": 963994, "position": 162432433}, {"id": 16, "top": 963994, "position": 272810302}, {"id": 17, "top": 963994, "position": 155684323}, {"id": 18, "top": 963994, "position": 320046008}, {"id": 19, "top": 963994, "position": 338332931}, {"id": 20, "top": 963994, "position": 298838140}, {"id": 21, "top": 963994, "position": 120499250}, {"id": 22, "top": 963994, "position": 125800908}, {"id": 23, "top": 963994, "position": 240998500}, {"id": 24, "top": 963994, "position": 161228511}, {"id": 25, "top": 963994, "position": 194834710}, {"id": 26, "top": 963994, "position": 194351816}, {"id": 27, "top": 963994, "position": 89651274}, {"id": 28, "top": 963994, "position": 18315886}, {"id": 29, "top": 963994, "position": 200074352}, {"id": 30, "top": 963994, "position": 14459910}, {"id": 31, "top": 963994, "position": 192481037}, {"id": 32, "top": 963994, "position": 195381583}, {"id": 33, "top": 963994, "position": 53214872}, {"id": 34, "top": 963994, "position": 235266166}, {"id": 35, "top": 963994, "position": 206201040}, {"id": 36, "top": 963994, "position": 126764869}, {"id": 37, "top": 963994, "position": 241485190}, {"id": 38, "top": 963994, "position": 203598013}, {"id": 39, "top": 963994, "position": 194837357}, {"id": 40, "top": 963994, "position": 379813636}, {"id": 41, "top": 963994, "position": 105287298}, {"id": 42, "top": 963994, "position": 52055820}, {"id": 43, "top": 963994, "position": 91579325}, {"id": 44, "top": 963994, "position": 172071753}, {"id": 45, "top": 963994, "position": 218237962}, {"id": 46, "top": 963994, "position": 187088979}, {"id": 47, "top": 963994, "position": 56393289}, {"id": 48, "top": 963994, "position": 110668135}, {"id": 49, "top": 963994, "position": 182107185}, {"id": 50, "top": 963994, "position": 137369895}, {"id": 51, "top": 963994, "position": 197358825}, {"id": 52, "top": 963994, "position": 216489749}, {"id": 53, "top": 963994, "position": 177528815}, {"id": 54, "top": 963994, "position": 186554218}, {"id": 55, "top": 963994, "position": 258693656}, {"id": 56, "top": 963994, "position": 230117078}, {"id": 57, "top": 963994, "position": 87724549}, {"id": 58, "top": 963994, "position": 134959160}, {"id": 59, "top": 963994, "position": 75191532}, {"id": 60, "top": 963994, "position": 214358950}, {"id": 61, "top": 963994, "position": 45789779}, {"id": 62, "top": 963994, "position": 176048589}, {"id": 63, "top": 963994, "position": 189323177}, {"id": 64, "top": 963994, "position": 67961502}, {"id": 65, "top": 963994, "position": 132921251}, {"id": 66, "top": 963994, "position": 326793966}, {"id": 67, "top": 963994, "position": 86519678}, {"id": 68, "top": 963994, "position": 119438289}, {"id": 69, "top": 963994, "position": 158428742}, {"id": 70, "top": 963994, "position": 206814526}, {"id": 71, "top": 963994, "position": 198247705}, {"id": 72, "top": 963994, "position": 160971719}, {"id": 73, "top": 963994, "position": 183677243}, {"id": 74, "top": 963994, "position": 113268835}, {"id": 75, "top": 963994, "position": 196462311}, {"id": 76, "top": 963994, "position": 156649537}, {"id": 77, "top": 963994, "position": 206715755}, {"id": 78, "top": 963994, "position": 198515411}, {"id": 79, "top": 963994, "position": 152311052}, {"id": 80, "top": 963994, "position": 126308455}, {"id": 81, "top": 963994, "position": 180266878}, {"id": 82, "top": 963994, "position": 148937565}, {"id": 83, "top": 963994, "position": 163977800}, {"id": 84, "top": 963994, "position": 200362437}, {"id": 85, "top": 963994, "position": 220480707}, {"id": 86, "top": 963994, "position": 73745049}, {"id": 87, "top": 963994, "position": 130622708}, {"id": 88, "top": 963994, "position": 253237459}, {"id": 89, "top": 963994, "position": 87226374}, {"id": 90, "top": 963994, "position": 5301975}, {"id": 91, "top": 963994, "position": 124654647}, {"id": 92, "top": 963994, "position": 109611660}, {"id": 93, "top": 963994, "position": 62659610}, {"id": 94, "top": 963994, "position": 187570740}, {"id": 95, "top": 963994, "position": 280273792}, {"id": 96, "top": 963994, "position": 166966103}, {"id": 97, "top": 963994, "position": 116159985}, {"id": 98, "top": 963994, "position": 215543549}, {"id": 99, "top": 963994, "position": 191059384}], "qualite": 0.2081746538960162, "temperature": 21.876730477240866}