{"tortoises": [{"id": 0, "top": 963610, "position": 95397390}, {"id": 1, "top": 963610, "position": 184588341}, {"id": 2, "top": 963610, "position": 53044615}, {"id": 3, "top": 963610, "position": 214546121}, {"id": 4, "top": 963610, "position": 181762352}, {"id": 5, "top": 963610, "position": 188812072}, {"id": 6, "top": 963610, "position": 257390302}, {"id": 7, "top": 963610, "position": 169247827}, {"id": 8, "top": 963610, "position": 223546371}, {"id": 9, "top": 963610, "position": 115535322}, {"id": 10, "top": 963610, "position": 128014790}, {"id": 11, "top": 963610, "position": 165738258}, {"id": 12, "top": 963610, "position": 256566773}, {"id": 13, "top": 963610, "position": 332081090}, {"id": 14, "top": 963610, "position": 171522580}, {"id": 15, "top": 963610, "position": 162367978}, {"id": 16, "top": 963610, "position": 272701630}, {"id": 17, "top": 963610, "position": 155624045}, {"id": 18, "top": 963610, "position": 319918520}, {"id": 19, "top": 963610, "position": 338258125}, {"id": 20, "top": 963610, "position": 298719100}, {"id": 21, "top": 963610, "position": 120451250}, {"id": 22, "top": 963610, "position": 125751150}, {"id": 23, "top": 963610, "position": 240902500}, {"id": 24, "top": 963610, "position": 161159655}, {"id": 25, "top": 963610, "position": 194757785}, {"id": 26, "top": 963610, "position": 194274647}, {"id": 27, "top": 963610, "position": 89615922}, {"id": 28, "top": 963610, "position": 18308590}, {"id": 29, "top": 963610, "position": 199994654}, {"id": 30, "top": 963610, "position": 14454150}, {"id": 31, "top": 963610, "position": 192404659}, {"id": 32, "top": 963610, "position": 195251407}, {"id": 33, "top": 963610, "position": 53203352}, {"id": 34, "top": 963610, "position": 235160182}, {"id": 35, "top": 963610, "position": 206130290}, {"id": 36, "top": 963610, "position": 126714725}, {"id": 37, "top": 963610, "position": 241370758}, {"id": 38, "top": 963610, "position": 203516094}, {"id": 39, "top": 963610, "position": 194759618}, {"id": 40, "top": 963610, "position": 379662340}, {"id": 41, "top": 963610, "position": 105242086}, {"id": 42, "top": 963610, "position": 52034868}, {"id": 43, "top": 963610, "position": 91542845}, {"id": 44, "top": 963610, "position": 172006401}, {"id": 45, "top": 963610, "position": 218151480}, {"id": 46, "top": 963610, "position": 187013673}, {"id": 47, "top": 963610, "position": 56371077}, {"id": 48, "top": 963610, "position": 110633971}, {"id": 49, "top": 963610, "position": 182040522}, {"id": 50, "top": 963610, "position": 137315055}, {"id": 51, "top": 963610, "position": 197280523}, {"id": 52, "top": 963610, "position": 216403198}, {"id": 53, "top": 963610, "position": 177457761}, {"id": 54, "top": 963610, "position": 186479401}, {"id": 55, "top": 963610, "position": 258572312}, {"id": 56, "top": 963610, "position": 230021942}, {"id": 57, "top": 963610, "position": 87675859}, {"id": 58, "top": 963610, "position": 134905400}, {"id": 59, "top": 963610, "position": 75161580}, {"id": 60, "top": 963610, "position": 214268523}, {"id": 61, "top": 963610, "position": 45771475}, {"id": 62, "top": 963610, "position": 175973682}, {"id": 63, "top": 963610, "position": 189245937}, {"id": 64, "top": 963610, "position": 67934430}, {"id": 65, "top": 963610, "position": 132856739}, {"id": 66, "top": 963610, "position": 326663790}, {"id": 67, "top": 963610, "position": 86483198}, {"id": 68, "top": 963610, "position": 119371665}, {"id": 69, "top": 963610, "position": 158365647}, {"id": 70, "top": 963610, "position": 206732705}, {"id": 71, "top": 963610, "position": 198168338}, {"id": 72, "top": 963610, "position": 160932167}, {"id": 73, "top": 963610, "position": 183581627}, {"id": 74, "top": 963610, "position": 113224375}, {"id": 75, "top": 963610, "position": 196384123}, {"id": 76, "top": 963610, "position": 156587215}, {"id": 77, "top": 963610, "position": 206579819}, {"id": 78, "top": 963610, "position": 198436698}, {"id": 79, "top": 963610, "position": 152250380}, {"id": 80, "top": 963610, "position": 126242253}, {"id": 81, "top": 963610, "position": 180195070}, {"id": 82, "top": 963610, "position": 148878345}, {"id": 83, "top": 963610, "position": 163912498}, {"id": 84, "top": 963610, "position": 200282498}, {"id": 85, "top": 963610, "position": 220437837}, {"id": 86, "top": 963610, "position": 73716018}, {"id": 87, "top": 963610, "position": 130569420}, {"id": 88, "top": 963610, "position": 253119571}, {"id": 89, "top": 963610, "position": 87199110}, {"id": 90, "top": 963610, "position": 5299863}, {"id": 91, "top": 963610, "position": 124584463}, {"id": 92, "top": 963610, "position": 109578588}, {"id": 93, "top": 963610, "position": 62634650}, {"id": 94, "top": 963610, "position": 187495986}, {"id": 95, "top": 963610, "position": 280121728}, {"id": 96, "top": 963610, "position": 166886417}, {"id": 97, "top": 963610, "position": 116117419}, {"id": 98, "top": 963610, "position": 215457217}, {"id": 99, "top": 963610, "position": 190983117}], "qualite": 0.2081746538960162, "temperature": 21.876730477240866}