{"tortoises": [{"id": 0, "top": 963619, "position": 156455028}, {"id": 1, "top": 963619, "position": 132704171}, {"id": 2, "top": 963619, "position": 171387975}, {"id": 3, "top": 963619, "position": 242592391}, {"id": 4, "top": 963619, "position": 199056407}, {"id": 5, "top": 963619, "position": 124447023}, {"id": 6, "top": 963619, "position": 196066647}, {"id": 7, "top": 963619, "position": 256220388}, {"id": 8, "top": 963619, "position": 370993315}, {"id": 9, "top": 963619, "position": 227179147}, {"id": 10, "top": 963619, "position": 84798472}, {"id": 11, "top": 963619, "position": 203714708}, {"id": 12, "top": 963619, "position": 127680496}, {"id": 13, "top": 963619, "position": 339193888}, {"id": 14, "top": 963619, "position": 156587697}, {"id": 15, "top": 963619, "position": 192074547}, {"id": 16, "top": 963619, "position": 135978367}, {"id": 17, "top": 963619, "position": 192243045}, {"id": 18, "top": 963619, "position": 159630993}, {"id": 19, "top": 963619, "position": 151589999}, {"id": 20, "top": 963619, "position": 204958005}, {"id": 21, "top": 963619, "position": 180149160}, {"id": 22, "top": 963619, "position": 181642675}, {"id": 23, "top": 963619, "position": 58299083}, {"id": 24, "top": 963619, "position": 115079012}, {"id": 25, "top": 963619, "position": 202689934}, {"id": 26, "top": 963619, "position": 159731091}, {"id": 27, "top": 963619, "position": 189792967}, {"id": 28, "top": 963619, "position": 161946336}, {"id": 29, "top": 963619, "position": 172533639}, {"id": 30, "top": 963619, "position": 42399388}, {"id": 31, "top": 963619, "position": 91269127}, {"id": 32, "top": 963619, "position": 161984223}, {"id": 33, "top": 963619, "position": 63253287}, {"id": 34, "top": 963619, "position": 118525137}, {"id": 35, "top": 963619, "position": 189306171}, {"id": 36, "top": 963619, "position": 278850243}, {"id": 37, "top": 963619, "position": 183736772}, {"id": 38, "top": 963619, "position": 280937812}, {"id": 39, "top": 963619, "position": 272704177}, {"id": 40, "top": 963619, "position": 146470088}, {"id": 41, "top": 963619, "position": 160132104}, {"id": 42, "top": 963619, "position": 77089450}, {"id": 43, "top": 963619, "position": 126173151}, {"id": 44, "top": 963619, "position": 95890997}, {"id": 45, "top": 963619, "position": 165014616}, {"id": 46, "top": 963619, "position": 128656307}, {"id": 47, "top": 963619, "position": 207383732}, {"id": 48, "top": 963619, "position": 50108148}, {"id": 49, "top": 963619, "position": 161879067}, {"id": 50, "top": 963619, "position": 220732019}, {"id": 51, "top": 963619, "position": 189049052}, {"id": 52, "top": 963619, "position": 185122649}, {"id": 53, "top": 963619, "position": 29872189}, {"id": 54, "top": 963619, "position": 138761136}, {"id": 55, "top": 963619, "position": 173831527}, {"id": 56, "top": 963619, "position": 172007844}, {"id": 57, "top": 963619, "position": 43362909}, {"id": 58, "top": 963619, "position": 207094772}, {"id": 59, "top": 963619, "position": 309321699}, {"id": 60, "top": 963619, "position": 133945009}, {"id": 61, "top": 963619, "position": 295831033}, {"id": 62, "top": 963619, "position": 362320744}, {"id": 63, "top": 963619, "position": 316067032}, {"id": 64, "top": 963619, "position": 69380568}, {"id": 65, "top": 963619, "position": 184258671}, {"id": 66, "top": 963619, "position": 124305828}, {"id": 67, "top": 963619, "position": 199692143}, {"id": 68, "top": 963619, "position": 222836927}, {"id": 69, "top": 963619, "position": 45290093}, {"id": 70, "top": 963619, "position": 36917152}, {"id": 71, "top": 963619, "position": 118204697}, {"id": 72, "top": 963619, "position": 359075412}, {"id": 73, "top": 963619, "position": 203323609}, {"id": 74, "top": 963619, "position": 37221731}, {"id": 75, "top": 963619, "position": 191024442}, {"id": 76, "top": 963619, "position": 321409815}, {"id": 77, "top": 963619, "position": 188486916}, {"id": 78, "top": 963619, "position": 103638060}, {"id": 79, "top": 963619, "position": 123343232}, {"id": 80, "top": 963619, "position": 197328386}, {"id": 81, "top": 963619, "position": 70344187}, {"id": 82, "top": 963619, "position": 185978455}, {"id": 83, "top": 963619, "position": 72271593}, {"id": 84, "top": 963619, "position": 118389498}, {"id": 85, "top": 963619, "position": 179596337}, {"id": 86, "top": 963619, "position": 196096670}, {"id": 87, "top": 963619, "position": 177188886}, {"id": 88, "top": 963619, "position": 197570075}, {"id": 89, "top": 963619, "position": 167188523}, {"id": 90, "top": 963619, "position": 213086570}, {"id": 91, "top": 963619, "position": 340157507}, {"id": 92, "top": 963619, "position": 222595989}, {"id": 93, "top": 963619, "position": 119221143}, {"id": 94, "top": 963619, "position": 200822451}, {"id": 95, "top": 963619, "position": 192053171}, {"id": 96, "top": 963619, "position": 180600146}, {"id": 97, "top": 963619, "position": 75162282}, {"id": 98, "top": 963619, "position": 54730235}, {"id": 99, "top": 963619, "position": 189133856}, {"id": 100, "top": 963619, "position": 129124539}, {"id": 101, "top": 963619, "position": 30835808}, {"id": 102, "top": 963619, "position": 194600462}, {"id": 103, "top": 963619, "position": 292192821}, {"id": 104, "top": 963619, "position": 126971153}, {"id": 105, "top": 963619, "position": 198207835}, {"id": 106, "top": 963619, "position": 221123069}, {"id": 107, "top": 963619, "position": 187502464}, {"id": 108, "top": 963619, "position": 200536003}, {"id": 109, "top": 963619, "position": 194651038}, {"id": 110, "top": 963619, "position": 137258825}, {"id": 111, "top": 963619, "position": 90098548}, {"id": 112, "top": 963619, "position": 170941002}, {"id": 113, "top": 963619, "position": 142335349}, {"id": 114, "top": 963619, "position": 98770852}, {"id": 115, "top": 963619, "position": 151769646}, {"id": 116, "top": 963619, "position": 115138427}, {"id": 117, "top": 963619, "position": 128266496}, {"id": 118, "top": 963619, "position": 201687091}, {"id": 119, "top": 963619, "position": 146791245}, {"id": 120, "top": 963619, "position": 215939271}, {"id": 121, "top": 963619, "position": 90580109}, {"id": 122, "top": 963619, "position": 167108508}, {"id": 123, "top": 963619, "position": 221246847}, {"id": 124, "top": 963619, "position": 110816185}, {"id": 125, "top": 963619, "position": 175034773}, {"id": 126, "top": 963619, "position": 79246844}, {"id": 127, "top": 963619, "position": 84798472}, {"id": 128, "top": 963619, "position": 66489711}, {"id": 129, "top": 963619, "position": 157185189}, {"id": 130, "top": 963619, "position": 176066855}, {"id": 131, "top": 963619, "position": 239941131}, {"id": 132, "top": 963619, "position": 106961709}, {"id": 133, "top": 963619, "position": 217777894}, {"id": 134, "top": 963619, "position": 186809034}, {"id": 135, "top": 963619, "position": 108888947}, {"id": 136, "top": 963619, "position": 178682286}, {"id": 137, "top": 963619, "position": 300649128}, {"id": 138, "top": 963619, "position": 165228552}, {"id": 139, "top": 963619, "position": 119487654}, {"id": 140, "top": 963619, "position": 201777907}, {"id": 141, "top": 963619, "position": 87949622}, {"id": 142, "top": 963619, "position": 46735586}, {"id": 143, "top": 963619, "position": 193321583}, {"id": 144, "top": 963619, "position": 179243833}, {"id": 145, "top": 963619, "position": 68416949}, {"id": 146, "top": 963619, "position": 195025468}, {"id": 147, "top": 963619, "position": 142615612}, {"id": 148, "top": 963619, "position": 204619431}, {"id": 149, "top": 963619, "position": 184186760}, {"id": 150, "top": 963619, "position": 157092275}, {"id": 151, "top": 963619, "position": 241868369}, {"id": 152, "top": 963619, "position": 185844680}, {"id": 153, "top": 963619, "position": 72753162}, {"id": 154, "top": 963619, "position": 108407742}, {"id": 155, "top": 963619, "position": 246543021}, {"id": 156, "top": 963619, "position": 204180354}, {"id": 157, "top": 963619, "position": 198228184}, {"id": 158, "top": 963619, "position": 19272380}, {"id": 159, "top": 963619, "position": 154831392}, {"id": 160, "top": 963619, "position": 176772729}, {"id": 161, "top": 963619, "position": 92025719}, {"id": 162, "top": 963619, "position": 183164662}, {"id": 163, "top": 963619, "position": 212959799}, {"id": 164, "top": 963619, "position": 188870899}, {"id": 165, "top": 963619, "position": 21199645}, {"id": 166, "top": 963619, "position": 307487675}, {"id": 167, "top": 963619, "position": 176870459}, {"id": 168, "top": 963619, "position": 130535591}, {"id": 169, "top": 963619, "position": 203119956}, {"id": 170, "top": 963619, "position": 185494716}, {"id": 171, "top": 963619, "position": 252675356}, {"id": 172, "top": 963619, "position": 102623503}, {"id": 173, "top": 963619, "position": 145506862}, {"id": 174, "top": 963619, "position": 130826146}, {"id": 175, "top": 963619, "position": 187904868}, {"id": 176, "top": 963619, "position": 199750937}, {"id": 177, "top": 963619, "position": 101133910}, {"id": 178, "top": 963619, "position": 181803180}, {"id": 179, "top": 963619, "position": 198719660}, {"id": 180, "top": 963619, "position": 199435511}, {"id": 181, "top": 963619, "position": 192861487}, {"id": 182, "top": 963619, "position": 169189567}, {"id": 183, "top": 963619, "position": 173929342}, {"id": 184, "top": 963619, "position": 131052184}, {"id": 185, "top": 963619, "position": 129678700}, {"id": 186, "top": 963619, "position": 269813320}, {"id": 187, "top": 963619, "position": 266922463}, {"id": 188, "top": 963619, "position": 85762756}, {"id": 189, "top": 963619, "position": 334375793}, {"id": 190, "top": 963619, "position": 148667554}, {"id": 191, "top": 963619, "position": 33726640}, {"id": 192, "top": 963619, "position": 161102922}, {"id": 193, "top": 963619, "position": 199996004}, {"id": 194, "top": 963619, "position": 160431864}, {"id": 195, "top": 963619, "position": 92762613}, {"id": 196, "top": 963619, "position": 200892208}, {"id": 197, "top": 963619, "position": 186941646}, {"id": 198, "top": 963619, "position": 113224920}, {"id": 199, "top": 963619, "position": 357502649}, {"id": 200, "top": 963619, "position": 163347810}, {"id": 201, "top": 963619, "position": 150142224}, {"id": 202, "top": 963619, "position": 63598854}, {"id": 203, "top": 963619, "position": 281638246}, {"id": 204, "top": 963619, "position": 192669607}, {"id": 205, "top": 963619, "position": 99133784}, {"id": 206, "top": 963619, "position": 103106925}, {"id": 207, "top": 963619, "position": 117561400}, {"id": 208, "top": 963619, "position": 146020408}, {"id": 209, "top": 963619, "position": 191490231}, {"id": 210, "top": 963619, "position": 279191492}, {"id": 211, "top": 963619, "position": 136999219}, {"id": 212, "top": 963619, "position": 143579231}, {"id": 213, "top": 963619, "position": 97325738}, {"id": 214, "top": 963619, "position": 178291870}, {"id": 215, "top": 963619, "position": 124306851}, {"id": 216, "top": 963619, "position": 44808342}, {"id": 217, "top": 963619, "position": 102956069}, {"id": 218, "top": 963619, "position": 145506469}, {"id": 219, "top": 963619, "position": 163333863}, {"id": 220, "top": 963619, "position": 230924572}, {"id": 221, "top": 963619, "position": 80798648}, {"id": 222, "top": 963619, "position": 185067281}, {"id": 223, "top": 963619, "position": 132016160}, {"id": 224, "top": 963619, "position": 194052829}, {"id": 225, "top": 963619, "position": 211046807}, {"id": 226, "top": 963619, "position": 136834430}, {"id": 227, "top": 963619, "position": 50589962}, {"id": 228, "top": 963619, "position": 199992390}, {"id": 229, "top": 963619, "position": 181401489}, {"id": 230, "top": 963619, "position": 134426304}, {"id": 231, "top": 963619, "position": 136719502}, {"id": 232, "top": 963619, "position": 222572291}, {"id": 233, "top": 963619, "position": 186899962}, {"id": 234, "top": 963619, "position": 286194843}, {"id": 235, "top": 963619, "position": 182417698}, {"id": 236, "top": 963619, "position": 92989382}, {"id": 237, "top": 963619, "position": 18308761}, {"id": 238, "top": 963619, "position": 109370469}, {"id": 239, "top": 963619, "position": 200737281}, {"id": 240, "top": 963619, "position": 261140749}, {"id": 241, "top": 963619, "position": 236038501}, {"id": 242, "top": 963619, "position": 163739165}, {"id": 243, "top": 963619, "position": 85280208}, {"id": 244, "top": 963619, "position": 150324564}, {"id": 245, "top": 963619, "position": 107059008}, {"id": 246, "top": 963619, "position": 205366331}, {"id": 247, "top": 963619, "position": 186201390}, {"id": 248, "top": 963619, "position": 140688374}, {"id": 249, "top": 963619, "position": 172969110}, {"id": 250, "top": 963619, "position": 258249892}, {"id": 251, "top": 963619, "position": 185996723}, {"id": 252, "top": 963619, "position": 363284363}, {"id": 253, "top": 963619, "position": 249664859}, {"id": 254, "top": 963619, "position": 234159417}, {"id": 255, "top": 963619, "position": 61760282}, {"id": 256, "top": 963619, "position": 197648201}, {"id": 257, "top": 963619, "position": 177793394}, {"id": 258, "top": 963619, "position": 181251710}, {"id": 259, "top": 963619, "position": 128576231}, {"id": 260, "top": 963619, "position": 157069897}, {"id": 261, "top": 963619, "position": 230135106}, {"id": 262, "top": 963619, "position": 231268560}, {"id": 263, "top": 963619, "position": 80461476}, {"id": 264, "top": 963619, "position": 127197708}, {"id": 265, "top": 963619, "position": 221296626}, {"id": 266, "top": 963619, "position": 77117572}, {"id": 267, "top": 963619, "position": 199110656}, {"id": 268, "top": 963619, "position": 174999035}, {"id": 269, "top": 963619, "position": 52035426}, {"id": 270, "top": 963619, "position": 192126229}, {"id": 271, "top": 963619, "position": 211996180}, {"id": 272, "top": 963619, "position": 249577321}, {"id": 273, "top": 963619, "position": 206995477}, {"id": 274, "top": 963619, "position": 102625644}, {"id": 275, "top": 963619, "position": 69862507}, {"id": 276, "top": 963619, "position": 321848746}, {"id": 277, "top": 963619, "position": 178269515}, {"id": 278, "top": 963619, "position": 82745711}, {"id": 279, "top": 963619, "position": 120453040}, {"id": 280, "top": 963619, "position": 75162237}, {"id": 281, "top": 963619, "position": 69380508}, {"id": 282, "top": 963619, "position": 112783678}, {"id": 283, "top": 963619, "position": 361357125}, {"id": 284, "top": 963619, "position": 215054505}, {"id": 285, "top": 963619, "position": 132717372}, {"id": 286, "top": 963619, "position": 168152674}, {"id": 287, "top": 963619, "position": 71307736}, {"id": 288, "top": 963619, "position": 82871164}, {"id": 289, "top": 963619, "position": 63599082}, {"id": 290, "top": 963619, "position": 187616546}, {"id": 291, "top": 963619, "position": 97325890}, {"id": 292, "top": 963619, "position": 28908570}, {"id": 293, "top": 963619, "position": 189425733}, {"id": 294, "top": 963619, "position": 195786621}, {"id": 295, "top": 963619, "position": 26017713}, {"id": 296, "top": 963619, "position": 123288504}, {"id": 297, "top": 963619, "position": 101264752}, {"id": 298, "top": 963619, "position": 184854075}, {"id": 299, "top": 963619, "position": 126715769}, {"id": 300, "top": 963619, "position": 92267166}, {"id": 301, "top": 963619, "position": 190458557}, {"id": 302, "top": 963619, "position": 107441173}, {"id": 303, "top": 963619, "position": 134139122}, {"id": 304, "top": 963619, "position": 228377703}, {"id": 305, "top": 963619, "position": 113561874}, {"id": 306, "top": 963619, "position": 23126840}, {"id": 307, "top": 963619, "position": 176088130}, {"id": 308, "top": 963619, "position": 369066077}, {"id": 309, "top": 963619, "position": 252468178}, {"id": 310, "top": 963619, "position": 203323609}, {"id": 311, "top": 963619, "position": 162363178}, {"id": 312, "top": 963619, "position": 67934748}, {"id": 313, "top": 963619, "position": 81425990}, {"id": 314, "top": 963619, "position": 178483906}, {"id": 315, "top": 963619, "position": 88610757}, {"id": 316, "top": 963619, "position": 138634406}, {"id": 317, "top": 963619, "position": 186382038}, {"id": 318, "top": 963619, "position": 207651224}, {"id": 319, "top": 963619, "position": 104961262}, {"id": 320, "top": 963619, "position": 336303031}, {"id": 321, "top": 963619, "position": 92025542}, {"id": 322, "top": 963619, "position": 192204872}, {"id": 323, "top": 963619, "position": 349793697}, {"id": 324, "top": 963619, "position": 170849593}, {"id": 325, "top": 963619, "position": 92145180}, {"id": 326, "top": 963619, "position": 40472091}, {"id": 327, "top": 963619, "position": 218837314}, {"id": 328, "top": 963619, "position": 172044539}, {"id": 329, "top": 963619, "position": 194107008}, {"id": 330, "top": 963619, "position": 176857739}, {"id": 331, "top": 963619, "position": 212774880}, {"id": 332, "top": 963619, "position": 112432010}, {"id": 333, "top": 963619, "position": 243795607}, {"id": 334, "top": 963619, "position": 148397326}, {"id": 335, "top": 963619, "position": 43362912}, {"id": 336, "top": 963619, "position": 267886082}, {"id": 337, "top": 963619, "position": 202140212}, {"id": 338, "top": 963619, "position": 100710722}, {"id": 339, "top": 963619, "position": 130570258}, {"id": 340, "top": 963619, "position": 211673065}, {"id": 341, "top": 963619, "position": 29872444}, {"id": 342, "top": 963619, "position": 124307334}, {"id": 343, "top": 963619, "position": 162011850}, {"id": 344, "top": 963619, "position": 64215396}, {"id": 345, "top": 963619, "position": 182545720}, {"id": 346, "top": 963619, "position": 180318257}, {"id": 347, "top": 963619, "position": 110838467}, {"id": 348, "top": 963619, "position": 176703891}, {"id": 349, "top": 963619, "position": 8672571}, {"id": 350, "top": 963619, "position": 205467454}, {"id": 351, "top": 963619, "position": 166169361}, {"id": 352, "top": 963619, "position": 191250780}, {"id": 353, "top": 963619, "position": 88653149}, {"id": 354, "top": 963619, "position": 161221024}, {"id": 355, "top": 963619, "position": 186461158}, {"id": 356, "top": 963619, "position": 198448663}, {"id": 357, "top": 963619, "position": 146979402}, {"id": 358, "top": 963619, "position": 101031515}, {"id": 359, "top": 963619, "position": 79980044}, {"id": 360, "top": 963619, "position": 45577204}, {"id": 361, "top": 963619, "position": 183087610}, {"id": 362, "top": 963619, "position": 186411171}, {"id": 363, "top": 963619, "position": 130190432}, {"id": 364, "top": 963619, "position": 322812365}, {"id": 365, "top": 963619, "position": 208426542}, {"id": 366, "top": 963619, "position": 105998002}, {"id": 367, "top": 963619, "position": 16381523}, {"id": 368, "top": 963619, "position": 252468178}, {"id": 369, "top": 963619, "position": 95811529}, {"id": 370, "top": 963619, "position": 143097678}, {"id": 371, "top": 963619, "position": 294867414}, {"id": 372, "top": 963619, "position": 207178027}, {"id": 373, "top": 963619, "position": 123267057}, {"id": 374, "top": 963619, "position": 119626924}, {"id": 375, "top": 963619, "position": 166706809}, {"id": 376, "top": 963619, "position": 132497323}, {"id": 377, "top": 963619, "position": 214476689}, {"id": 378, "top": 963619, "position": 198392529}, {"id": 379, "top": 963619, "position": 292910084}, {"id": 380, "top": 963619, "position": 102488043}, {"id": 381, "top": 963619, "position": 184051229}, {"id": 382, "top": 963619, "position": 96361805}, {"id": 383, "top": 963619, "position": 219460554}, {"id": 384, "top": 963619, "position": 73235242}, {"id": 385, "top": 963619, "position": 103589204}, {"id": 386, "top": 963619, "position": 104666387}, {"id": 387, "top": 963619, "position": 142832140}, {"id": 388, "top": 963619, "position": 202906744}, {"id": 389, "top": 963619, "position": 344975602}, {"id": 390, "top": 963619, "position": 278485891}, {"id": 391, "top": 963619, "position": 199120953}, {"id": 392, "top": 963619, "position": 117820974}, {"id": 393, "top": 963619, "position": 234767709}, {"id": 394, "top": 963619, "position": 385447600}, {"id": 395, "top": 963619, "position": 249066953}, {"id": 396, "top": 963619, "position": 206214466}, {"id": 397, "top": 963619, "position": 183083727}, {"id": 398, "top": 963619, "position": 141128613}, {"id": 399, "top": 963619, "position": 141171257}, {"id": 400, "top": 963619, "position": 194870764}, {"id": 401, "top": 963619, "position": 123396604}, {"id": 402, "top": 963619, "position": 197541736}, {"id": 403, "top": 963619, "position": 76347402}, {"id": 404, "top": 963619, "position": 201640851}, {"id": 405, "top": 963619, "position": 118975612}, {"id": 406, "top": 963619, "position": 128342196}, {"id": 407, "top": 963619, "position": 111297747}, {"id": 408, "top": 963619, "position": 224224669}, {"id": 409, "top": 963619, "position": 187266778}, {"id": 410, "top": 963619, "position": 187347633}, {"id": 411, "top": 963619, "position": 197020721}, {"id": 412, "top": 963619, "position": 171342772}, {"id": 413, "top": 963619, "position": 42881110}, {"id": 414, "top": 963619, "position": 133943531}, {"id": 415, "top": 963619, "position": 179381389}, {"id": 416, "top": 963619, "position": 110334778}, {"id": 417, "top": 963619, "position": 21199618}, {"id": 418, "top": 963619, "position": 165632790}, {"id": 419, "top": 963619, "position": 187200946}, {"id": 420, "top": 963619, "position": 162369158}, {"id": 421, "top": 963619, "position": 271828937}, {"id": 422, "top": 963619, "position": 99166463}, {"id": 423, "top": 963619, "position": 71307971}, {"id": 424, "top": 963619, "position": 64562323}, {"id": 425, "top": 963619, "position": 121414080}, {"id": 426, "top": 963619, "position": 173433642}, {"id": 427, "top": 963619, "position": 230309006}, {"id": 428, "top": 963619, "position": 175378422}, {"id": 429, "top": 963619, "position": 156299780}, {"id": 430, "top": 963619, "position": 205658693}, {"id": 431, "top": 963619, "position": 193141307}, {"id": 432, "top": 963619, "position": 125271685}, {"id": 433, "top": 963619, "position": 171992931}, {"id": 434, "top": 963619, "position": 204822524}, {"id": 435, "top": 963619, "position": 115152365}, {"id": 436, "top": 963619, "position": 332448555}, {"id": 437, "top": 963619, "position": 152786620}, {"id": 438, "top": 963619, "position": 204044529}, {"id": 439, "top": 963619, "position": 135219830}, {"id": 440, "top": 963619, "position": 116354064}, {"id": 441, "top": 963619, "position": 248774655}, {"id": 442, "top": 963619, "position": 121897687}, {"id": 443, "top": 963619, "position": 117756608}, {"id": 444, "top": 963619, "position": 165743535}, {"id": 445, "top": 963619, "position": 159250851}, {"id": 446, "top": 963619, "position": 120452375}, {"id": 447, "top": 963619, "position": 224334564}, {"id": 448, "top": 963619, "position": 132007460}, {"id": 449, "top": 963619, "position": 96361900}, {"id": 450, "top": 963619, "position": 136889803}, {"id": 451, "top": 963619, "position": 185550142}, {"id": 452, "top": 963619, "position": 61189673}, {"id": 453, "top": 963619, "position": 56853521}, {"id": 454, "top": 963619, "position": 164822532}, {"id": 455, "top": 963619, "position": 132978987}, {"id": 456, "top": 963619, "position": 324739603}, {"id": 457, "top": 963619, "position": 169639529}, {"id": 458, "top": 963619, "position": 211453691}, {"id": 459, "top": 963619, "position": 200376928}, {"id": 460, "top": 963619, "position": 167670336}, {"id": 461, "top": 963619, "position": 175377425}, {"id": 462, "top": 963619, "position": 209580840}, {"id": 463, "top": 963619, "position": 170458156}, {"id": 464, "top": 963619, "position": 187073585}, {"id": 465, "top": 963619, "position": 115856422}, {"id": 466, "top": 963619, "position": 215850656}, {"id": 467, "top": 963619, "position": 193999855}, {"id": 468, "top": 963619, "position": 249119416}, {"id": 469, "top": 963619, "position": 76125666}, {"id": 470, "top": 963619, "position": 133461109}, {"id": 471, "top": 963619, "position": 63599766}, {"id": 472, "top": 963619, "position": 158299460}, {"id": 473, "top": 963619, "position": 125208301}, {"id": 474, "top": 963619, "position": 143097138}, {"id": 475, "top": 963619, "position": 148876431}, {"id": 476, "top": 963619, "position": 182123991}, {"id": 477, "top": 963619, "position": 260177130}, {"id": 478, "top": 963619, "position": 68416882}, {"id": 479, "top": 963619, "position": 59744240}, {"id": 480, "top": 963619, "position": 182693833}, {"id": 481, "top": 963619, "position": 88652948}, {"id": 482, "top": 963619, "position": 202815231}, {"id": 483, "top": 963619, "position": 154933929}, {"id": 484, "top": 963619, "position": 24572262}, {"id": 485, "top": 963619, "position": 203608809}, {"id": 486, "top": 963619, "position": 274631415}, {"id": 487, "top": 963619, "position": 105516522}, {"id": 488, "top": 963619, "position": 112498098}, {"id": 489, "top": 963619, "position": 148808028}, {"id": 490, "top": 963619, "position": 196354556}, {"id": 491, "top": 963619, "position": 113707042}, {"id": 492, "top": 963619, "position": 196239384}, {"id": 493, "top": 963619, "position": 365211601}, {"id": 494, "top": 963619, "position": 219880336}, {"id": 495, "top": 963619, "position": 149360945}, {"id": 496, "top": 963619, "position": 171139440}, {"id": 497, "top": 963619, "position": 182937683}, {"id": 498, "top": 963619, "position": 274514102}, {"id": 499, "top": 963619, "position": 202100836}], "qualite": 0.9834735838576971, "temperature": 19.197404847555088}