{"tortoises": [{"id": 0, "top": 963626, "position": 156456564}, {"id": 1, "top": 963626, "position": 132705135}, {"id": 2, "top": 963626, "position": 171389829}, {"id": 3, "top": 963626, "position": 242594981}, {"id": 4, "top": 963626, "position": 199057701}, {"id": 5, "top": 963626, "position": 124447477}, {"id": 6, "top": 963626, "position": 196068259}, {"id": 7, "top": 963626, "position": 256223188}, {"id": 8, "top": 963626, "position": 370996010}, {"id": 9, "top": 963626, "position": 227181101}, {"id": 10, "top": 963626, "position": 84799088}, {"id": 11, "top": 963626, "position": 203716066}, {"id": 12, "top": 963626, "position": 127680965}, {"id": 13, "top": 963626, "position": 339196352}, {"id": 14, "top": 963626, "position": 156588775}, {"id": 15, "top": 963626, "position": 192076176}, {"id": 16, "top": 963626, "position": 135978899}, {"id": 17, "top": 963626, "position": 192243375}, {"id": 18, "top": 963626, "position": 159632365}, {"id": 19, "top": 963626, "position": 151591300}, {"id": 20, "top": 963626, "position": 204959505}, {"id": 21, "top": 963626, "position": 180149262}, {"id": 22, "top": 963626, "position": 181644306}, {"id": 23, "top": 963626, "position": 58299304}, {"id": 24, "top": 963626, "position": 115080520}, {"id": 25, "top": 963626, "position": 202691236}, {"id": 26, "top": 963626, "position": 159732015}, {"id": 27, "top": 963626, "position": 189793871}, {"id": 28, "top": 963626, "position": 161947797}, {"id": 29, "top": 963626, "position": 172535159}, {"id": 30, "top": 963626, "position": 42399436}, {"id": 31, "top": 963626, "position": 91269928}, {"id": 32, "top": 963626, "position": 161985319}, {"id": 33, "top": 963626, "position": 63254015}, {"id": 34, "top": 963626, "position": 118525998}, {"id": 35, "top": 963626, "position": 189307888}, {"id": 36, "top": 963626, "position": 278852406}, {"id": 37, "top": 963626, "position": 183738308}, {"id": 38, "top": 963626, "position": 280938902}, {"id": 39, "top": 963626, "position": 272706158}, {"id": 40, "top": 963626, "position": 146471152}, {"id": 41, "top": 963626, "position": 160133354}, {"id": 42, "top": 963626, "position": 77090185}, {"id": 43, "top": 963626, "position": 126173256}, {"id": 44, "top": 963626, "position": 95891261}, {"id": 45, "top": 963626, "position": 165014779}, {"id": 46, "top": 963626, "position": 128657056}, {"id": 47, "top": 963626, "position": 207385358}, {"id": 48, "top": 963626, "position": 50108636}, {"id": 49, "top": 963626, "position": 161880932}, {"id": 50, "top": 963626, "position": 220733549}, {"id": 51, "top": 963626, "position": 189050133}, {"id": 52, "top": 963626, "position": 185125246}, {"id": 53, "top": 963626, "position": 29872406}, {"id": 54, "top": 963626, "position": 138762144}, {"id": 55, "top": 963626, "position": 173832880}, {"id": 56, "top": 963626, "position": 172008957}, {"id": 57, "top": 963626, "position": 43363233}, {"id": 58, "top": 963626, "position": 207096784}, {"id": 59, "top": 963626, "position": 309323946}, {"id": 60, "top": 963626, "position": 133945817}, {"id": 61, "top": 963626, "position": 295833182}, {"id": 62, "top": 963626, "position": 362323376}, {"id": 63, "top": 963626, "position": 316069328}, {"id": 64, "top": 963626, "position": 69381072}, {"id": 65, "top": 963626, "position": 184260022}, {"id": 66, "top": 963626, "position": 124307298}, {"id": 67, "top": 963626, "position": 199693455}, {"id": 68, "top": 963626, "position": 222838429}, {"id": 69, "top": 963626, "position": 45290422}, {"id": 70, "top": 963626, "position": 36917228}, {"id": 71, "top": 963626, "position": 118205435}, {"id": 72, "top": 963626, "position": 359077848}, {"id": 73, "top": 963626, "position": 203325086}, {"id": 74, "top": 963626, "position": 37222235}, {"id": 75, "top": 963626, "position": 191025839}, {"id": 76, "top": 963626, "position": 321411810}, {"id": 77, "top": 963626, "position": 188488595}, {"id": 78, "top": 963626, "position": 103639621}, {"id": 79, "top": 963626, "position": 123344128}, {"id": 80, "top": 963626, "position": 197330016}, {"id": 81, "top": 963626, "position": 70344698}, {"id": 82, "top": 963626, "position": 185979911}, {"id": 83, "top": 963626, "position": 72271808}, {"id": 84, "top": 963626, "position": 118390226}, {"id": 85, "top": 963626, "position": 179597557}, {"id": 86, "top": 963626, "position": 196097901}, {"id": 87, "top": 963626, "position": 177190767}, {"id": 88, "top": 963626, "position": 197571489}, {"id": 89, "top": 963626, "position": 167189009}, {"id": 90, "top": 963626, "position": 213088442}, {"id": 91, "top": 963626, "position": 340159978}, {"id": 92, "top": 963626, "position": 222597606}, {"id": 93, "top": 963626, "position": 119221775}, {"id": 94, "top": 963626, "position": 200824230}, {"id": 95, "top": 963626, "position": 192054792}, {"id": 96, "top": 963626, "position": 180601707}, {"id": 97, "top": 963626, "position": 75162828}, {"id": 98, "top": 963626, "position": 54730690}, {"id": 99, "top": 963626, "position": 189135536}, {"id": 100, "top": 963626, "position": 129125470}, {"id": 101, "top": 963626, "position": 30836032}, {"id": 102, "top": 963626, "position": 194601604}, {"id": 103, "top": 963626, "position": 292195348}, {"id": 104, "top": 963626, "position": 126972774}, {"id": 105, "top": 963626, "position": 198208876}, {"id": 106, "top": 963626, "position": 221124842}, {"id": 107, "top": 963626, "position": 187503869}, {"id": 108, "top": 963626, "position": 200537621}, {"id": 109, "top": 963626, "position": 194652452}, {"id": 110, "top": 963626, "position": 137259098}, {"id": 111, "top": 963626, "position": 90098807}, {"id": 112, "top": 963626, "position": 170942377}, {"id": 113, "top": 963626, "position": 142337246}, {"id": 114, "top": 963626, "position": 98771950}, {"id": 115, "top": 963626, "position": 151770675}, {"id": 116, "top": 963626, "position": 115139798}, {"id": 117, "top": 963626, "position": 128266755}, {"id": 118, "top": 963626, "position": 201688511}, {"id": 119, "top": 963626, "position": 146791559}, {"id": 120, "top": 963626, "position": 215941973}, {"id": 121, "top": 963626, "position": 90581123}, {"id": 122, "top": 963626, "position": 167109432}, {"id": 123, "top": 963626, "position": 221248315}, {"id": 124, "top": 963626, "position": 110816990}, {"id": 125, "top": 963626, "position": 175036137}, {"id": 126, "top": 963626, "position": 79246924}, {"id": 127, "top": 963626, "position": 84799088}, {"id": 128, "top": 963626, "position": 66490194}, {"id": 129, "top": 963626, "position": 157186353}, {"id": 130, "top": 963626, "position": 176067876}, {"id": 131, "top": 963626, "position": 239942874}, {"id": 132, "top": 963626, "position": 106962486}, {"id": 133, "top": 963626, "position": 217779476}, {"id": 134, "top": 963626, "position": 186810574}, {"id": 135, "top": 963626, "position": 108889738}, {"id": 136, "top": 963626, "position": 178684283}, {"id": 137, "top": 963626, "position": 300651312}, {"id": 138, "top": 963626, "position": 165229436}, {"id": 139, "top": 963626, "position": 119488326}, {"id": 140, "top": 963626, "position": 201779368}, {"id": 141, "top": 963626, "position": 87950866}, {"id": 142, "top": 963626, "position": 46735931}, {"id": 143, "top": 963626, "position": 193323100}, {"id": 144, "top": 963626, "position": 179245515}, {"id": 145, "top": 963626, "position": 68417446}, {"id": 146, "top": 963626, "position": 195027108}, {"id": 147, "top": 963626, "position": 142616648}, {"id": 148, "top": 963626, "position": 204620678}, {"id": 149, "top": 963626, "position": 184188365}, {"id": 150, "top": 963626, "position": 157092410}, {"id": 151, "top": 963626, "position": 241870126}, {"id": 152, "top": 963626, "position": 185846241}, {"id": 153, "top": 963626, "position": 72753884}, {"id": 154, "top": 963626, "position": 108408085}, {"id": 155, "top": 963626, "position": 246544295}, {"id": 156, "top": 963626, "position": 204181881}, {"id": 157, "top": 963626, "position": 198229938}, {"id": 158, "top": 963626, "position": 19272520}, {"id": 159, "top": 963626, "position": 154831714}, {"id": 160, "top": 963626, "position": 176774365}, {"id": 161, "top": 963626, "position": 92025870}, {"id": 162, "top": 963626, "position": 183165872}, {"id": 163, "top": 963626, "position": 212961346}, {"id": 164, "top": 963626, "position": 188872005}, {"id": 165, "top": 963626, "position": 21199803}, {"id": 166, "top": 963626, "position": 307490020}, {"id": 167, "top": 963626, "position": 176871678}, {"id": 168, "top": 963626, "position": 130536928}, {"id": 169, "top": 963626, "position": 203122042}, {"id": 170, "top": 963626, "position": 185497257}, {"id": 171, "top": 963626, "position": 252676900}, {"id": 172, "top": 963626, "position": 102624721}, {"id": 173, "top": 963626, "position": 145508136}, {"id": 174, "top": 963626, "position": 130827467}, {"id": 175, "top": 963626, "position": 187906716}, {"id": 176, "top": 963626, "position": 199752423}, {"id": 177, "top": 963626, "position": 101134288}, {"id": 178, "top": 963626, "position": 181804191}, {"id": 179, "top": 963626, "position": 198721349}, {"id": 180, "top": 963626, "position": 199437394}, {"id": 181, "top": 963626, "position": 192863014}, {"id": 182, "top": 963626, "position": 169191639}, {"id": 183, "top": 963626, "position": 173931568}, {"id": 184, "top": 963626, "position": 131053136}, {"id": 185, "top": 963626, "position": 129679813}, {"id": 186, "top": 963626, "position": 269815280}, {"id": 187, "top": 963626, "position": 266924402}, {"id": 188, "top": 963626, "position": 85763078}, {"id": 189, "top": 963626, "position": 334378222}, {"id": 190, "top": 963626, "position": 148668457}, {"id": 191, "top": 963626, "position": 33726900}, {"id": 192, "top": 963626, "position": 161104504}, {"id": 193, "top": 963626, "position": 199997337}, {"id": 194, "top": 963626, "position": 160432692}, {"id": 195, "top": 963626, "position": 92763789}, {"id": 196, "top": 963626, "position": 200893419}, {"id": 197, "top": 963626, "position": 186942920}, {"id": 198, "top": 963626, "position": 113226270}, {"id": 199, "top": 963626, "position": 357505246}, {"id": 200, "top": 963626, "position": 163348895}, {"id": 201, "top": 963626, "position": 150143629}, {"id": 202, "top": 963626, "position": 63599316}, {"id": 203, "top": 963626, "position": 281641046}, {"id": 204, "top": 963626, "position": 192671514}, {"id": 205, "top": 963626, "position": 99135377}, {"id": 206, "top": 963626, "position": 103107660}, {"id": 207, "top": 963626, "position": 117561540}, {"id": 208, "top": 963626, "position": 146021841}, {"id": 209, "top": 963626, "position": 191491385}, {"id": 210, "top": 963626, "position": 279193304}, {"id": 211, "top": 963626, "position": 137000711}, {"id": 212, "top": 963626, "position": 143580274}, {"id": 213, "top": 963626, "position": 97326076}, {"id": 214, "top": 963626, "position": 178293331}, {"id": 215, "top": 963626, "position": 124307754}, {"id": 216, "top": 963626, "position": 44808675}, {"id": 217, "top": 963626, "position": 102957321}, {"id": 218, "top": 963626, "position": 145507526}, {"id": 219, "top": 963626, "position": 163335312}, {"id": 220, "top": 963626, "position": 230927288}, {"id": 221, "top": 963626, "position": 80798822}, {"id": 222, "top": 963626, "position": 185068089}, {"id": 223, "top": 963626, "position": 132017322}, {"id": 224, "top": 963626, "position": 194054452}, {"id": 225, "top": 963626, "position": 211047930}, {"id": 226, "top": 963626, "position": 136834880}, {"id": 227, "top": 963626, "position": 50590355}, {"id": 228, "top": 963626, "position": 199993926}, {"id": 229, "top": 963626, "position": 181402798}, {"id": 230, "top": 963626, "position": 134427179}, {"id": 231, "top": 963626, "position": 136720844}, {"id": 232, "top": 963626, "position": 222573801}, {"id": 233, "top": 963626, "position": 186900988}, {"id": 234, "top": 963626, "position": 286196922}, {"id": 235, "top": 963626, "position": 182419283}, {"id": 236, "top": 963626, "position": 92989491}, {"id": 237, "top": 963626, "position": 18308894}, {"id": 238, "top": 963626, "position": 109371759}, {"id": 239, "top": 963626, "position": 200739297}, {"id": 240, "top": 963626, "position": 261142646}, {"id": 241, "top": 963626, "position": 236040290}, {"id": 242, "top": 963626, "position": 163740005}, {"id": 243, "top": 963626, "position": 85281162}, {"id": 244, "top": 963626, "position": 150325656}, {"id": 245, "top": 963626, "position": 107060548}, {"id": 246, "top": 963626, "position": 205367836}, {"id": 247, "top": 963626, "position": 186202610}, {"id": 248, "top": 963626, "position": 140689396}, {"id": 249, "top": 963626, "position": 172970335}, {"id": 250, "top": 963626, "position": 258251768}, {"id": 251, "top": 963626, "position": 185998263}, {"id": 252, "top": 963626, "position": 363287002}, {"id": 253, "top": 963626, "position": 249666098}, {"id": 254, "top": 963626, "position": 234161118}, {"id": 255, "top": 963626, "position": 61760534}, {"id": 256, "top": 963626, "position": 197649573}, {"id": 257, "top": 963626, "position": 177794374}, {"id": 258, "top": 963626, "position": 181253040}, {"id": 259, "top": 963626, "position": 128576469}, {"id": 260, "top": 963626, "position": 157071038}, {"id": 261, "top": 963626, "position": 230136844}, {"id": 262, "top": 963626, "position": 231270240}, {"id": 263, "top": 963626, "position": 80461924}, {"id": 264, "top": 963626, "position": 127198632}, {"id": 265, "top": 963626, "position": 221298023}, {"id": 266, "top": 963626, "position": 77118860}, {"id": 267, "top": 963626, "position": 199112224}, {"id": 268, "top": 963626, "position": 175000763}, {"id": 269, "top": 963626, "position": 52035804}, {"id": 270, "top": 963626, "position": 192128966}, {"id": 271, "top": 963626, "position": 211997720}, {"id": 272, "top": 963626, "position": 249579134}, {"id": 273, "top": 963626, "position": 206996859}, {"id": 274, "top": 963626, "position": 102625945}, {"id": 275, "top": 963626, "position": 69862707}, {"id": 276, "top": 963626, "position": 321851084}, {"id": 277, "top": 963626, "position": 178270810}, {"id": 278, "top": 963626, "position": 82746320}, {"id": 279, "top": 963626, "position": 120453250}, {"id": 280, "top": 963626, "position": 75162955}, {"id": 281, "top": 963626, "position": 69381174}, {"id": 282, "top": 963626, "position": 112784141}, {"id": 283, "top": 963626, "position": 361359750}, {"id": 284, "top": 963626, "position": 215056633}, {"id": 285, "top": 963626, "position": 132717980}, {"id": 286, "top": 963626, "position": 168154907}, {"id": 287, "top": 963626, "position": 71308408}, {"id": 288, "top": 963626, "position": 82871962}, {"id": 289, "top": 963626, "position": 63599154}, {"id": 290, "top": 963626, "position": 187617874}, {"id": 291, "top": 963626, "position": 97326190}, {"id": 292, "top": 963626, "position": 28908780}, {"id": 293, "top": 963626, "position": 189427512}, {"id": 294, "top": 963626, "position": 195787615}, {"id": 295, "top": 963626, "position": 26017902}, {"id": 296, "top": 963626, "position": 123290156}, {"id": 297, "top": 963626, "position": 101266484}, {"id": 298, "top": 963626, "position": 184855624}, {"id": 299, "top": 963626, "position": 126717173}, {"id": 300, "top": 963626, "position": 92267624}, {"id": 301, "top": 963626, "position": 190460216}, {"id": 302, "top": 963626, "position": 107441376}, {"id": 303, "top": 963626, "position": 134139274}, {"id": 304, "top": 963626, "position": 228379362}, {"id": 305, "top": 963626, "position": 113562003}, {"id": 306, "top": 963626, "position": 23127020}, {"id": 307, "top": 963626, "position": 176088788}, {"id": 308, "top": 963626, "position": 369068758}, {"id": 309, "top": 963626, "position": 252470012}, {"id": 310, "top": 963626, "position": 203325086}, {"id": 311, "top": 963626, "position": 162364172}, {"id": 312, "top": 963626, "position": 67935028}, {"id": 313, "top": 963626, "position": 81426283}, {"id": 314, "top": 963626, "position": 178484769}, {"id": 315, "top": 963626, "position": 88611674}, {"id": 316, "top": 963626, "position": 138634526}, {"id": 317, "top": 963626, "position": 186383431}, {"id": 318, "top": 963626, "position": 207653296}, {"id": 319, "top": 963626, "position": 104961295}, {"id": 320, "top": 963626, "position": 336305474}, {"id": 321, "top": 963626, "position": 92026436}, {"id": 322, "top": 963626, "position": 192206335}, {"id": 323, "top": 963626, "position": 349796238}, {"id": 324, "top": 963626, "position": 170851047}, {"id": 325, "top": 963626, "position": 92145334}, {"id": 326, "top": 963626, "position": 40472247}, {"id": 327, "top": 963626, "position": 218839344}, {"id": 328, "top": 963626, "position": 172045759}, {"id": 329, "top": 963626, "position": 194108236}, {"id": 330, "top": 963626, "position": 176858966}, {"id": 331, "top": 963626, "position": 212775639}, {"id": 332, "top": 963626, "position": 112432415}, {"id": 333, "top": 963626, "position": 243797378}, {"id": 334, "top": 963626, "position": 148398404}, {"id": 335, "top": 963626, "position": 43363234}, {"id": 336, "top": 963626, "position": 267888028}, {"id": 337, "top": 963626, "position": 202141619}, {"id": 338, "top": 963626, "position": 100710876}, {"id": 339, "top": 963626, "position": 130571716}, {"id": 340, "top": 963626, "position": 211674736}, {"id": 341, "top": 963626, "position": 29872626}, {"id": 342, "top": 963626, "position": 124307742}, {"id": 343, "top": 963626, "position": 162012873}, {"id": 344, "top": 963626, "position": 64215471}, {"id": 345, "top": 963626, "position": 182547231}, {"id": 346, "top": 963626, "position": 180319550}, {"id": 347, "top": 963626, "position": 110839181}, {"id": 348, "top": 963626, "position": 176705166}, {"id": 349, "top": 963626, "position": 8672634}, {"id": 350, "top": 963626, "position": 205468763}, {"id": 351, "top": 963626, "position": 166171151}, {"id": 352, "top": 963626, "position": 191251814}, {"id": 353, "top": 963626, "position": 88653469}, {"id": 354, "top": 963626, "position": 161221570}, {"id": 355, "top": 963626, "position": 186461863}, {"id": 356, "top": 963626, "position": 198450602}, {"id": 357, "top": 963626, "position": 146979553}, {"id": 358, "top": 963626, "position": 101032837}, {"id": 359, "top": 963626, "position": 79980814}, {"id": 360, "top": 963626, "position": 45577246}, {"id": 361, "top": 963626, "position": 183088940}, {"id": 362, "top": 963626, "position": 186412436}, {"id": 363, "top": 963626, "position": 130191272}, {"id": 364, "top": 963626, "position": 322814710}, {"id": 365, "top": 963626, "position": 208428517}, {"id": 366, "top": 963626, "position": 105999190}, {"id": 367, "top": 963626, "position": 16381642}, {"id": 368, "top": 963626, "position": 252470012}, {"id": 369, "top": 963626, "position": 95812082}, {"id": 370, "top": 963626, "position": 143097915}, {"id": 371, "top": 963626, "position": 294869556}, {"id": 372, "top": 963626, "position": 207179324}, {"id": 373, "top": 963626, "position": 123267414}, {"id": 374, "top": 963626, "position": 119627806}, {"id": 375, "top": 963626, "position": 166706979}, {"id": 376, "top": 963626, "position": 132498969}, {"id": 377, "top": 963626, "position": 214478523}, {"id": 378, "top": 963626, "position": 198394440}, {"id": 379, "top": 963626, "position": 292911567}, {"id": 380, "top": 963626, "position": 102489437}, {"id": 381, "top": 963626, "position": 184052566}, {"id": 382, "top": 963626, "position": 96362975}, {"id": 383, "top": 963626, "position": 219463116}, {"id": 384, "top": 963626, "position": 73235886}, {"id": 385, "top": 963626, "position": 103589375}, {"id": 386, "top": 963626, "position": 104667476}, {"id": 387, "top": 963626, "position": 142832903}, {"id": 388, "top": 963626, "position": 202908036}, {"id": 389, "top": 963626, "position": 344978108}, {"id": 390, "top": 963626, "position": 278487914}, {"id": 391, "top": 963626, "position": 199122410}, {"id": 392, "top": 963626, "position": 117822577}, {"id": 393, "top": 963626, "position": 234768856}, {"id": 394, "top": 963626, "position": 385450400}, {"id": 395, "top": 963626, "position": 249067680}, {"id": 396, "top": 963626, "position": 206215964}, {"id": 397, "top": 963626, "position": 183085883}, {"id": 398, "top": 963626, "position": 141130468}, {"id": 399, "top": 963626, "position": 141171768}, {"id": 400, "top": 963626, "position": 194872113}, {"id": 401, "top": 963626, "position": 123398206}, {"id": 402, "top": 963626, "position": 197543612}, {"id": 403, "top": 963626, "position": 76348596}, {"id": 404, "top": 963626, "position": 201642217}, {"id": 405, "top": 963626, "position": 118976151}, {"id": 406, "top": 963626, "position": 128343008}, {"id": 407, "top": 963626, "position": 111299133}, {"id": 408, "top": 963626, "position": 224226365}, {"id": 409, "top": 963626, "position": 187268335}, {"id": 410, "top": 963626, "position": 187348649}, {"id": 411, "top": 963626, "position": 197022380}, {"id": 412, "top": 963626, "position": 171343563}, {"id": 413, "top": 963626, "position": 42881423}, {"id": 414, "top": 963626, "position": 133943888}, {"id": 415, "top": 963626, "position": 179382539}, {"id": 416, "top": 963626, "position": 110335069}, {"id": 417, "top": 963626, "position": 21199772}, {"id": 418, "top": 963626, "position": 165633150}, {"id": 419, "top": 963626, "position": 187202126}, {"id": 420, "top": 963626, "position": 162370698}, {"id": 421, "top": 963626, "position": 271831198}, {"id": 422, "top": 963626, "position": 99166674}, {"id": 423, "top": 963626, "position": 71308255}, {"id": 424, "top": 963626, "position": 64563132}, {"id": 425, "top": 963626, "position": 121415116}, {"id": 426, "top": 963626, "position": 173434293}, {"id": 427, "top": 963626, "position": 230311624}, {"id": 428, "top": 963626, "position": 175378632}, {"id": 429, "top": 963626, "position": 156300907}, {"id": 430, "top": 963626, "position": 205660140}, {"id": 431, "top": 963626, "position": 193142644}, {"id": 432, "top": 963626, "position": 125272623}, {"id": 433, "top": 963626, "position": 171993967}, {"id": 434, "top": 963626, "position": 204824201}, {"id": 435, "top": 963626, "position": 115153649}, {"id": 436, "top": 963626, "position": 332450970}, {"id": 437, "top": 963626, "position": 152787019}, {"id": 438, "top": 963626, "position": 204046372}, {"id": 439, "top": 963626, "position": 135221086}, {"id": 440, "top": 963626, "position": 116355478}, {"id": 441, "top": 963626, "position": 248775953}, {"id": 442, "top": 963626, "position": 121899043}, {"id": 443, "top": 963626, "position": 117757042}, {"id": 444, "top": 963626, "position": 165744473}, {"id": 445, "top": 963626, "position": 159251754}, {"id": 446, "top": 963626, "position": 120453250}, {"id": 447, "top": 963626, "position": 224336204}, {"id": 448, "top": 963626, "position": 132009186}, {"id": 449, "top": 963626, "position": 96362600}, {"id": 450, "top": 963626, "position": 136889971}, {"id": 451, "top": 963626, "position": 185551506}, {"id": 452, "top": 963626, "position": 61190433}, {"id": 453, "top": 963626, "position": 56853934}, {"id": 454, "top": 963626, "position": 164823990}, {"id": 455, "top": 963626, "position": 132980639}, {"id": 456, "top": 963626, "position": 324741962}, {"id": 457, "top": 963626, "position": 169641313}, {"id": 458, "top": 963626, "position": 211455407}, {"id": 459, "top": 963626, "position": 200378947}, {"id": 460, "top": 963626, "position": 167670828}, {"id": 461, "top": 963626, "position": 175379581}, {"id": 462, "top": 963626, "position": 209582246}, {"id": 463, "top": 963626, "position": 170459323}, {"id": 464, "top": 963626, "position": 187074669}, {"id": 465, "top": 963626, "position": 115857556}, {"id": 466, "top": 963626, "position": 215852224}, {"id": 467, "top": 963626, "position": 194000636}, {"id": 468, "top": 963626, "position": 249119869}, {"id": 469, "top": 963626, "position": 76126598}, {"id": 470, "top": 963626, "position": 133462597}, {"id": 471, "top": 963626, "position": 63600382}, {"id": 472, "top": 963626, "position": 158301148}, {"id": 473, "top": 963626, "position": 125209858}, {"id": 474, "top": 963626, "position": 143098893}, {"id": 475, "top": 963626, "position": 148876977}, {"id": 476, "top": 963626, "position": 182125314}, {"id": 477, "top": 963626, "position": 260179020}, {"id": 478, "top": 963626, "position": 68417527}, {"id": 479, "top": 963626, "position": 59744988}, {"id": 480, "top": 963626, "position": 182695142}, {"id": 481, "top": 963626, "position": 88653592}, {"id": 482, "top": 963626, "position": 202816687}, {"id": 483, "top": 963626, "position": 154935763}, {"id": 484, "top": 963626, "position": 24572445}, {"id": 485, "top": 963626, "position": 203610384}, {"id": 486, "top": 963626, "position": 274633410}, {"id": 487, "top": 963626, "position": 105516921}, {"id": 488, "top": 963626, "position": 112498140}, {"id": 489, "top": 963626, "position": 148809289}, {"id": 490, "top": 963626, "position": 196355914}, {"id": 491, "top": 963626, "position": 113707868}, {"id": 492, "top": 963626, "position": 196240377}, {"id": 493, "top": 963626, "position": 365214254}, {"id": 494, "top": 963626, "position": 219881923}, {"id": 495, "top": 963626, "position": 149362030}, {"id": 496, "top": 963626, "position": 171140827}, {"id": 497, "top": 963626, "position": 182938821}, {"id": 498, "top": 963626, "position": 274516832}, {"id": 499, "top": 963626, "position": 202102152}], "qualite": 0.9834735838576971, "temperature": 19.197404847555088}